nginx_logs_parser_and_process/DI.py
nginx_logs_parser_and_process/__init__.py
nginx_logs_parser_and_process/cli.py
nginx_logs_parser_and_process/application/NginxToDatabase.py
nginx_logs_parser_and_process/application/__init__.py
nginx_logs_parser_and_process/domain/__init__.py
nginx_logs_parser_and_process/domain/DataProcessor/EliminateUnnecessaryData.py
nginx_logs_parser_and_process/domain/DataProcessor/NormalizeModelData.py
nginx_logs_parser_and_process/domain/DataProcessor/PersistIntoDatabase.py
nginx_logs_parser_and_process/domain/DataProcessor/__init__.py
nginx_logs_parser_and_process/domain/Logs/ReadAllLogsFileIntoMemoryUsingPandas.py
nginx_logs_parser_and_process/domain/Logs/__init__.py
nginx_logs_parser_and_process/domain/Server/FilesSynchronizationError.py
nginx_logs_parser_and_process/domain/Server/Server.py
nginx_logs_parser_and_process/domain/Server/SynchronizeRemoteNginxLogsWithLocalRepository.py
nginx_logs_parser_and_process/domain/Server/__init__.py
nginx_logs_parser_and_process/domain/Tables/__init__.py
nginx_logs_parser_and_process/domain/Tables/tables.py
nginx_logs_parser_and_process/infrastructure/CanadaThreeDatabase.py
nginx_logs_parser_and_process/infrastructure/Database.py
nginx_logs_parser_and_process/infrastructure/LocalSqliteDatabase.py
nginx_logs_parser_and_process/infrastructure/__init__.py
nginx_logs_parser_and_process-1.0.27.dist-info/METADATA
nginx_logs_parser_and_process-1.0.27.dist-info/WHEEL
nginx_logs_parser_and_process-1.0.27.dist-info/entry_points.txt
nginx_logs_parser_and_process-1.0.27.dist-info/top_level.txt
nginx_logs_parser_and_process-1.0.27.dist-info/RECORD
